comfyui_workflow_templates_media_image/__init__.py
comfyui_workflow_templates_media_image/templates/01_get_started_text_to_image-1.webp
comfyui_workflow_templates_media_image/templates/01_get_started_text_to_image.json
comfyui_workflow_templates_media_image/templates/02_qwen_Image_edit_subgraphed-1.webp
comfyui_workflow_templates_media_image/templates/02_qwen_Image_edit_subgraphed.json
comfyui_workflow_templates_media_image/templates/3d_hunyuan3d_image_to_model-1.webp
comfyui_workflow_templates_media_image/templates/3d_hunyuan3d_image_to_model.json
comfyui_workflow_templates_media_image/templates/default-1.webp
comfyui_workflow_templates_media_image/templates/default.json
comfyui_workflow_templates_media_image/templates/flux1_dev_uso_reference_image_gen-1.webp
comfyui_workflow_templates_media_image/templates/flux1_dev_uso_reference_image_gen-2.webp
comfyui_workflow_templates_media_image/templates/flux1_dev_uso_reference_image_gen.json
comfyui_workflow_templates_media_image/templates/flux1_krea_dev-1.webp
comfyui_workflow_templates_media_image/templates/flux1_krea_dev.json
comfyui_workflow_templates_media_image/templates/flux_canny_model_example-1.webp
comfyui_workflow_templates_media_image/templates/flux_canny_model_example-2.webp
comfyui_workflow_templates_media_image/templates/flux_canny_model_example.json
comfyui_workflow_templates_media_image/templates/flux_depth_lora_example-1.webp
comfyui_workflow_templates_media_image/templates/flux_depth_lora_example-2.webp
comfyui_workflow_templates_media_image/templates/flux_depth_lora_example.json
comfyui_workflow_templates_media_image/templates/flux_dev_checkpoint_example-1.webp
comfyui_workflow_templates_media_image/templates/flux_dev_checkpoint_example.json
comfyui_workflow_templates_media_image/templates/flux_dev_full_text_to_image-1.webp
comfyui_workflow_templates_media_image/templates/flux_dev_full_text_to_image.json
comfyui_workflow_templates_media_image/templates/flux_fill_inpaint_example-1.webp
comfyui_workflow_templates_media_image-0.3.55.dist-info/METADATA
comfyui_workflow_templates_media_image-0.3.55.dist-info/WHEEL
comfyui_workflow_templates_media_image-0.3.55.dist-info/top_level.txt
comfyui_workflow_templates_media_image-0.3.55.dist-info/RECORD
