Metadata-Version: 2.4
Name: comfyui-workflow-templates-media-image
Version: 0.3.55
Summary: Media bundle containing image workflow assets
License-Expression: MIT
Requires-Python: >=3.9
